CHANGELOG
LICENSE
MANIFEST.in
README.md
setup.cfg
setup.py
Flask_Pilot.egg-info/PKG-INFO
Flask_Pilot.egg-info/SOURCES.txt
Flask_Pilot.egg-info/dependency_links.txt
Flask_Pilot.egg-info/entry_points.txt
Flask_Pilot.egg-info/not-zip-safe
Flask_Pilot.egg-info/pbr.json
Flask_Pilot.egg-info/requires.txt
Flask_Pilot.egg-info/top_level.txt
flask_pilot/__init__.py
flask_pilot/__init__.pyc
flask_pilot/cmd.py
flask_pilot/cmd.pyc
flask_pilot/skeleton/server.py.tpl
flask_pilot/skeleton/default/__init__.py
flask_pilot/skeleton/default/config.py
flask_pilot/skeleton/default/model.py
flask_pilot/skeleton/default/views.py
flask_pilot/skeleton/default/static/css/style.css
flask_pilot/skeleton/default/static/img/blank
flask_pilot/skeleton/default/static/js/app.js
flask_pilot/skeleton/default/static/vendor/bootstrap/css/bootstrap-theme.css
flask_pilot/skeleton/default/static/vendor/bootstrap/css/bootstrap-theme.css.map
flask_pilot/skeleton/default/static/vendor/bootstrap/css/bootstrap-theme.min.css
flask_pilot/skeleton/default/static/vendor/bootstrap/css/bootstrap.css
flask_pilot/skeleton/default/static/vendor/bootstrap/css/bootstrap.css.map
flask_pilot/skeleton/default/static/vendor/bootstrap/css/bootstrap.min.css
flask_pilot/skeleton/default/static/vendor/bootstrap/fonts/glyphicons-halflings-regular.eot
flask_pilot/skeleton/default/static/vendor/bootstrap/fonts/glyphicons-halflings-regular.svg
flask_pilot/skeleton/default/static/vendor/bootstrap/fonts/glyphicons-halflings-regular.ttf
flask_pilot/skeleton/default/static/vendor/bootstrap/fonts/glyphicons-halflings-regular.woff
flask_pilot/skeleton/default/static/vendor/bootstrap/js/bootstrap.js
flask_pilot/skeleton/default/static/vendor/bootstrap/js/bootstrap.min.js
flask_pilot/skeleton/default/static/vendor/bootswatch/README
flask_pilot/skeleton/default/static/vendor/bootswatch/amelia.css
flask_pilot/skeleton/default/static/vendor/bootswatch/cerulean.css
flask_pilot/skeleton/default/static/vendor/bootswatch/cosmo.css
flask_pilot/skeleton/default/static/vendor/bootswatch/cyborg.css
flask_pilot/skeleton/default/static/vendor/bootswatch/darkly.css
flask_pilot/skeleton/default/static/vendor/bootswatch/flatly.css
flask_pilot/skeleton/default/static/vendor/bootswatch/fonts.css
